ddlparser/__init__.py
ddlparser/compare.py
ddlparser/ddl_parser.py
ddlparser/parser.py
ddlparser/parsetab.py
ddlparser/tokens.py
ddlparser/utils.py
ddlparser/apps/__init__.py
ddlparser/apps/cli_app.py
ddlparser/dialects/__init__.py
ddlparser/dialects/bigquery.py
ddlparser/dialects/hql.py
ddlparser/dialects/mssql.py
ddlparser/dialects/mysql.py
ddlparser/dialects/oracle.py
ddlparser/dialects/redshift.py
ddlparser/dialects/snowflake.py
ddlparser/dialects/spark_sql.py
ddlparser/dialects/sql.py
ddlparser/output/__init__.py
ddlparser/output/common.py
ddlparser/output/dialects.py
ddlparser-1.1.dist-info/LICENSE
ddlparser-1.1.dist-info/METADATA
ddlparser-1.1.dist-info/WHEEL
ddlparser-1.1.dist-info/entry_points.txt
ddlparser-1.1.dist-info/top_level.txt
ddlparser-1.1.dist-info/RECORD
