Metadata-Version: 2.1
Name: ddlparser
Version: 1.1
Summary: parse sql , compare two .sql file , generate optimization hint for your sql and various other utilities
Home-page: https://github.com/koustreak/dot.parser
Author: Koushik Dutta
Author-email: dot.py@yahoo.com
License: MIT
Classifier: License :: OSI Approved :: MIT License
Classifier: Programming Language :: Python
Classifier: Programming Language :: Python :: 3
Classifier: Programming Language :: Python :: 3.9
Classifier: Programming Language :: Python :: Implementation :: CPython
Classifier: Programming Language :: Python :: Implementation :: PyPy
Requires-Python: >=3.9.0
License-File: LICENSE
Requires-Dist: colorama (==0.4.6)
Requires-Dist: commonmark (==0.9.1)
Requires-Dist: ply (==3.11)
Requires-Dist: pyfiglet (==0.8.post1)
Requires-Dist: Pygments (==2.14.0)
Requires-Dist: rich (==13.0.1)
Requires-Dist: tqdm (==4.64.1)
